paper_code-0.5.0.dist-info/licenses/LICENSE
src/ai_service.py
src/banner.py
src/config.py
src/detector.py
src/generator.py
src/main.py
paper_code-0.5.0.dist-info/METADATA
paper_code-0.5.0.dist-info/WHEEL
paper_code-0.5.0.dist-info/entry_points.txt
paper_code-0.5.0.dist-info/top_level.txt
paper_code-0.5.0.dist-info/RECORD
