Metadata-Version: 2.4
Name: paper-code
Version: 0.5.0
Summary: Interactive Project Documentation Generator for AI-Native Development
Author-email: Nguyen Minh Giau <minhgiau04041998@gmail.com>
Project-URL: Homepage, https://github.com/minhgiau998/paper-code
Project-URL: Bug Tracker, https://github.com/minhgiau998/paper-code/issues
Project-URL: Source Code, https://github.com/minhgiau998/paper-code
Requires-Python: >=3.10
License-File: LICENSE
Requires-Dist: setuptools>=80.0.0
Requires-Dist: typer>=0.9.0
Requires-Dist: jinja2>=3.1.2
Requires-Dist: inquirer>=3.1.4
Requires-Dist: rich>=13.7.0
Requires-Dist: click>=8.1.7
Requires-Dist: pyfiglet>=1.0.4
Requires-Dist: pathlib2>=2.3.7
Requires-Dist: openai>=1.0.0
Requires-Dist: python-dotenv>=1.0.0
Dynamic: license-file
